salesmachine/consumer.py
salesmachine/__init__.py
salesmachine/version.py
salesmachine/request.py
salesmachine/client.py
salesmachine/utils.py
salesmachine/test/consumer.py
salesmachine/test/__init__.py
salesmachine/test/request.py
salesmachine/test/module.py
salesmachine/test/client.py
salesmachine/test/utils.py
salesmachine_python-1.0.1.dist-info/RECORD
salesmachine_python-1.0.1.dist-info/top_level.txt
salesmachine_python-1.0.1.dist-info/metadata.json
salesmachine_python-1.0.1.dist-info/DESCRIPTION.rst
salesmachine_python-1.0.1.dist-info/METADATA
salesmachine_python-1.0.1.dist-info/WHEEL
