Metadata-Version: 2.0
Name: salesmachine-python
Version: 1.0.1
Summary: The hassle-free way to integrate Salesmachine.io into any python application.
Home-page: https://github.com/salesmachine-io/salesmachine-python
Author: Salesmachine
Author-email: team@salesmachine.io
License: MIT License
Platform: UNKNOWN
Requires-Dist: python-dateutil
Requires-Dist: requests
Requires-Dist: six
